kmlorm/__init__.py
kmlorm/_version.py
kmlorm/py.typed
kmlorm/core/__init__.py
kmlorm/core/exceptions.py
kmlorm/core/managers.py
kmlorm/core/querysets.py
kmlorm/exports/__init__.py
kmlorm/models/__init__.py
kmlorm/models/base.py
kmlorm/models/folder.py
kmlorm/models/multigeometry.py
kmlorm/models/path.py
kmlorm/models/placemark.py
kmlorm/models/point.py
kmlorm/models/polygon.py
kmlorm/parsers/__init__.py
kmlorm/parsers/kml_file.py
kmlorm/parsers/xml_parser.py
kmlorm/spatial/__init__.py
kmlorm/spatial/calculations.py
kmlorm/spatial/constants.py
kmlorm/spatial/exceptions.py
kmlorm/spatial/strategies.py
kmlorm/tests/__init__.py
kmlorm/tests/conftest.py
kmlorm/tests/test_api_docs_examples.py
kmlorm/tests/test_api_functionality.py
kmlorm/tests/test_base.py
kmlorm/tests/test_basic.py
kmlorm/tests/test_coordinate_docs.py
kmlorm/tests/test_core_docs.py
kmlorm/tests/test_examples_documentation.py
kmlorm/tests/test_exceptions_docs.old
kmlorm/tests/test_exceptions_docs.py
kmlorm/tests/test_folder.py
kmlorm/tests/test_geometry_recursive_collection.py
kmlorm/tests/test_index_docs.py
kmlorm/tests/test_kml_file.py
kmlorm/tests/test_kmlfile_docs.py
kmlorm/tests/test_manager_children_method.py
kmlorm/tests/test_managers_docs.py
kmlorm/tests/test_managers_extra.py
kmlorm/tests/test_models_docs.py
kmlorm/tests/test_multigeometry.py
kmlorm/tests/test_path.py
kmlorm/tests/test_placemark.py
kmlorm/tests/test_point_extra.py
kmlorm/tests/test_polygon.py
kmlorm/tests/test_queryset.py
kmlorm/tests/test_querysets_docs.py
kmlorm/tests/test_querysets_extra.py
kmlorm/tests/test_quickstart_examples.py
kmlorm/tests/test_recursive_all_behavior.py
kmlorm/tests/test_spatial_calculations.py
kmlorm/tests/test_spatial_distances_to_many.py
kmlorm/tests/test_spatial_docs.py
kmlorm/tests/test_spatial_edge_cases.py
kmlorm/tests/test_spatial_interpolation.py
kmlorm/tests/test_spatial_strategies.py
kmlorm/tests/test_tutorial_examples.py
kmlorm/tests/test_tutorial_field_lookups_exact.py
kmlorm-1.1.1.dist-info/licenses/LICENSE
kmlorm-1.1.1.dist-info/METADATA
kmlorm-1.1.1.dist-info/WHEEL
kmlorm-1.1.1.dist-info/top_level.txt
kmlorm-1.1.1.dist-info/RECORD
