Metadata-Version: 2.4
Name: kmlorm
Version: 1.1.1
Summary: A Django-style ORM for KML (Keyhole Markup Language) files
Author-email: Jack Nerad <kmlorm.project@gmail.com>
License: MIT
Project-URL: Homepage, https://github.com/stbrie/kmlorm
Project-URL: Documentation, https://kmlorm.readthedocs.io
Project-URL: Repository, https://github.com/stbrie/kmlorm.git
Project-URL: Bug Tracker, https://github.com/stbrie/kmlorm/issues
Keywords: kml,orm,gis,geospatial,django-style,google-earth
Classifier: Development Status :: 4 - Beta
Classifier: Intended Audience :: Developers
Classifier: Intended Audience :: Science/Research
Classifier: License :: OSI Approved :: MIT License
Classifier: Operating System :: OS Independent
Classifier: Programming Language :: Python :: 3
Classifier: Programming Language :: Python :: 3.11
Classifier: Programming Language :: Python :: 3.12
Classifier: Topic :: Scientific/Engineering :: GIS
Classifier: Topic :: Software Development :: Libraries :: Python Modules
Requires-Python: >=3.11
License-File: LICENSE
Requires-Dist: lxml
Provides-Extra: dev
Requires-Dist: pytest>=6.0; extra == "dev"
Requires-Dist: pytest-cov; extra == "dev"
Requires-Dist: black; extra == "dev"
Requires-Dist: flake8; extra == "dev"
Requires-Dist: mypy; extra == "dev"
Requires-Dist: isort; extra == "dev"
Requires-Dist: pre-commit; extra == "dev"
Provides-Extra: docs
Requires-Dist: sphinx; extra == "docs"
Requires-Dist: sphinx-rtd-theme; extra == "docs"
Requires-Dist: sphinx-autodoc-typehints; extra == "docs"
Provides-Extra: all
Requires-Dist: kmlorm[dev,docs]; extra == "all"
Dynamic: license-file
